streamlit_likedislike/__init__.py
streamlit_likedislike/frontend/build/asset-manifest.json
streamlit_likedislike/frontend/build/bootstrap.min.css
streamlit_likedislike/frontend/build/index.html
streamlit_likedislike/frontend/build/precache-manifest.7937682da2fdc10df4016edae5cae8a1.js
streamlit_likedislike/frontend/build/precache-manifest.8f32c9056b5103a864c0ab333e8a18d4.js
streamlit_likedislike/frontend/build/precache-manifest.cc48e98894ecd176200d9792511fccc3.js
streamlit_likedislike/frontend/build/service-worker.js
streamlit_likedislike/frontend/build/static/css/main.c6d044e3.chunk.css
streamlit_likedislike/frontend/build/static/css/main.c6d044e3.chunk.css.map
streamlit_likedislike/frontend/build/static/css/main.de9c1f8e.chunk.css
streamlit_likedislike/frontend/build/static/css/main.de9c1f8e.chunk.css.map
streamlit_likedislike/frontend/build/static/js/2.12481390.chunk.js
streamlit_likedislike/frontend/build/static/js/2.12481390.chunk.js.LICENSE.txt
streamlit_likedislike/frontend/build/static/js/2.12481390.chunk.js.map
streamlit_likedislike/frontend/build/static/js/2.1f2b4149.chunk.js
streamlit_likedislike/frontend/build/static/js/2.1f2b4149.chunk.js.LICENSE.txt
streamlit_likedislike/frontend/build/static/js/2.1f2b4149.chunk.js.map
streamlit_likedislike/frontend/build/static/js/main.373b998f.chunk.js
streamlit_likedislike/frontend/build/static/js/main.373b998f.chunk.js.map
streamlit_likedislike/frontend/build/static/js/main.8afd56f1.chunk.js
streamlit_likedislike/frontend/build/static/js/main.8afd56f1.chunk.js.map
streamlit_likedislike/frontend/build/static/js/main.91721807.chunk.js
streamlit_likedislike/frontend/build/static/js/main.91721807.chunk.js.map
streamlit_likedislike/frontend/build/static/js/runtime-main.bad378fd.js
streamlit_likedislike/frontend/build/static/js/runtime-main.bad378fd.js.map
streamlit_likedislike-0.0.8.dist-info/LICENSE
streamlit_likedislike-0.0.8.dist-info/METADATA
streamlit_likedislike-0.0.8.dist-info/WHEEL
streamlit_likedislike-0.0.8.dist-info/top_level.txt
streamlit_likedislike-0.0.8.dist-info/RECORD
